CHANGES
LICENSE
README.md
setup.py
ebookconverter/AutoDelete.py
ebookconverter/AutoRebuild.py
ebookconverter/CSV.py
ebookconverter/Candidates.py
ebookconverter/EbookConverter.py
ebookconverter/FileInfo.py
ebookconverter/Notifier.py
ebookconverter/PGMarc.py
ebookconverter/ReloadWorkflow.py
ebookconverter/UpdateFromWorkflow.py
ebookconverter/Version.py
ebookconverter/__init__.py
ebookconverter.egg-info/PKG-INFO
ebookconverter.egg-info/SOURCES.txt
ebookconverter.egg-info/dependency_links.txt
ebookconverter.egg-info/requires.txt
ebookconverter.egg-info/top_level.txt
ebookconverter/utils/ReparseCredits.py
ebookconverter/utils/forget_book.py
ebookconverter/utils/process_img_log.py
ebookconverter/utils/remove_extra_credits.py
ebookconverter/utils/test_email.py
ebookconverter/writers/BlueskyWriter.py
ebookconverter/writers/CoverWriter.py
ebookconverter/writers/FacebookWriter.py
ebookconverter/writers/HTMLWriter.py
ebookconverter/writers/MastodonWriter.py
ebookconverter/writers/QRCodeWriter.py
ebookconverter/writers/RDFWriter.py
ebookconverter/writers/UpdateWriter.py
ebookconverter/writers/__init__.py
scripts/autodelete
scripts/autorebuild
scripts/cron-csv-catalog
scripts/cron-dopush-social.sh
scripts/cron-dopush.sh
scripts/cron-jekyll.sh
scripts/cron-latesttitles.sh
scripts/cron-rdf-catalog
scripts/cron-rebuild-files.sh
scripts/cron-reindex.sh
scripts/dev-jekyll.sh
scripts/ebookconverter
scripts/fileinfo
scripts/make_csv
scripts/pgmarc
scripts/postbluesky
scripts/prod-jekyll.sh
scripts/reload_workflow
scripts/txt-tarball
scripts/update_from_workflow