Metadata-Version: 2.1
Name: ebookconverter
Version: 0.10.6
Summary: The Project Gutenberg tool to orchestrate ebook generation.
Home-page: https://github.com/gutenbergtools/ebookconverter/
Author: Eric Hellman
Author-email: eric@hellman.org
License: GPL v3
Platform: OS-independent
Classifier: License :: OSI Approved :: GNU General Public License (GPL)
Classifier: Environment :: Console
Classifier: Operating System :: OS Independent
Classifier: Intended Audience :: Other Audience
Classifier: Development Status :: 4 - Beta
Classifier: Programming Language :: Python
Classifier: Programming Language :: Python :: 3.9
License-File: LICENSE
Requires-Dist: ebookmaker>=0.13.7
Requires-Dist: setproctitle==1.1.10
Requires-Dist: requests_oauthlib>=1.2.0
Requires-Dist: rdflib>=4.2.2
Requires-Dist: qrcode>=6.1
Requires-Dist: libgutenberg[postgres]>=0.10.33
Requires-Dist: pymarc>=5.2.3
